[
  {
    "id": 6,
    "date": "2026-05-22",
    "title": "The Discipline Era",
    "path": "/issues/issue-006.html",
    "preview": "GTM engineering hits institutional maturity with niche signals, defined roles, salary benchmarks, and proof that AI drives quota."
  },
  {
    "id": 5,
    "date": "2026-05-15",
    "title": "Agents Execute, Prompts Lead",
    "path": "/issues/issue-005.html",
    "preview": "Sierra hits $15B, Clay MCP goes live, and GTM engineer prompts become the new source code."
  },
  {
    "id": 4,
    "date": "2026-05-08",
    "title": "Agents That Transact",
    "path": "/issues/issue-004.html",
    "preview": "The week AI agents gained ability to think, act, and pay—completing the agentic GTM stack"
  },
  {
    "id": 3,
    "date": "2026-05-01",
    "title": "Agents Take Infrastructure",
    "path": "/issues/issue-003.html",
    "preview": "The week AI agents moved from GTM experiments to production CRM and pipeline infrastructure"
  },
  {
    "id": 2,
    "date": "2026-04-24",
    "title": "Signal Architecture",
    "path": "/issues/issue-002.html",
    "preview": "How GTM engineers are building smarter signal layers, not just faster outbound pipes"
  },
  {
    "id": 1,
    "date": "2026-04-17",
    "title": "Agentic Shift",
    "path": "/issues/issue-001.html",
    "preview": "GTM infrastructure moves from tools to actors as Clay, Mutiny, and Relevance AI ship agents."
  }
]
